tinyrange/__init__.py
tinyrange-0.1.1.dist-info/METADATA
tinyrange-0.1.1.dist-info/WHEEL
tinyrange-0.1.1.dist-info/RECORD
